<RECIPE>
<TI>Soupe ensoleillée</TI>
<IN quantity="4">carottes</IN>
<IN quantity="2">courgette</IN>
<IN quantity="1">poivron</IN>
<IN quantity="2">pommes de terre</IN>
<IN quantity="1">oignon</IN>
<IN quantity="1 gousse">ail</IN>
<IN quantity="1">bouillon de volaille</IN>
<IN quantity="">curry</IN>
<IN quantity="">curcuma</IN>
<IN quantity="">poivre</IN>
<IN quantity="">sel</IN>
<IN quantity="">eau</IN>
<US>louche</US>
<US>mixeur plongeant</US>
<US>blendeur chauffant</US>
<US>couteau</US>
<US>casserole</US>
<US>couvercle</US>
<US>économe</US>
<US>couteau</US>
<US>mijoteuse</US>
<PR>
    Etape 1
    Laver, éplucher les carottes, et les couper en rondelles.
    Etape 2
    Laver, et couper les autres légumes en morceaux.
    Etape 3
    Mettre le tout dans une casserole avec le bouillon, le curry, et le curcuma.
    Etape 4
    Couvrir d'eau, et cuire à couvert pendant 30 min, jusqu'à ce que tous les légumes soient tendres.
    Etape 5
    Mixer, et rajouter de l'eau jusqu'à obtenir la consistance voulue.
    Etape 6
    Rectifier l'assaisonnment avant de servir.
</PR>
</RECIPE>
